{"cameraMode":{"drawMode":0,"name":"Shaded","section":"Shading Mode"},"sceneLighting":true,"audioPlay":false,"sceneViewState":{"showFog":true,"showMaterialUpdate":false,"showSkybox":true,"showFlares":true,"showImageEffects":true,"showParticleSystems":true},"in2DMode":false,"pivot":{"x":-17.544599533081056,"y":8.554410934448243,"z":1830.1234130859375},"rotation":{"x":0.10248315334320069,"y":0.7658157348632813,"z":-0.12450192123651505,"w":0.6221106648445129},"size":1.22756028175354,"orthographic":false}